handyfuncs/__init__.py
handyfuncs/automation.py
handyfuncs/manipulation.py
handyfuncs-0.0.2.dist-info/LICENSE
handyfuncs-0.0.2.dist-info/METADATA
handyfuncs-0.0.2.dist-info/WHEEL
handyfuncs-0.0.2.dist-info/top_level.txt
handyfuncs-0.0.2.dist-info/RECORD
