Metadata-Version: 2.1
Name: handyfuncs
Version: 0.0.2
Summary: Handy functions for manipulating data and automating processes
Home-page: https://github.com/porteverte/handyfuncs
Author: Porte Verte
Author-email: Port Verte <porte_verte@outlook.com>
Project-URL: Homepage, https://github.com/porteverte/handyfuncs
Project-URL: Issues, https://github.com/porteverte/handyfuncs/issues
Classifier: Programming Language :: Python :: 3
Classifier: License :: OSI Approved :: MIT License
Classifier: Operating System :: OS Independent
Requires-Python: >=3.8
License-File: LICENSE
